xmind2json/__init__.py
xmind2json/main.py
xmind2json/xreader.py
xmind2json/zenreader.py
xmind2json-1.1.0.dist-info/LICENSE
xmind2json-1.1.0.dist-info/METADATA
xmind2json-1.1.0.dist-info/WHEEL
xmind2json-1.1.0.dist-info/entry_points.txt
xmind2json-1.1.0.dist-info/top_level.txt
xmind2json-1.1.0.dist-info/RECORD
