Metadata-Version: 2.1
Name: xmind2json
Version: 1.1.0
Summary: Convert xmind to json or xml file.
Home-page: https://github.com/chencanxin/xmind2json
Author: hichencanxin
Author-email: hichencanxin@qq.com
License: UNKNOWN
Keywords: xmind parser converter json xml
Platform: UNKNOWN
Classifier: License :: OSI Approved :: MIT License
Classifier: Topic :: Software Development
Classifier: Topic :: Utilities
Classifier: Operating System :: Microsoft :: Windows
Classifier: Operating System :: MacOS :: MacOS X
Classifier: Programming Language :: Python :: 3.4
Classifier: Programming Language :: Python :: 3.5
Classifier: Programming Language :: Python :: 3.6
Classifier: Programming Language :: Python :: 3.7
Classifier: Programming Language :: Python :: 3.8
License-File: LICENSE
